temapi/__init__.py
temapi/api/__init__.py
temapi/api/_credit.py
temapi/api/_info.py
temapi/api/_orders.py
temapi/api/_utils.py
temapi/models/__init__.py
temapi/models/_common.py
temapi/models/_credit.py
temapi/models/_info.py
temapi/models/_orders.py
tem_api-0.1.8.dist-info/LICENSE
tem_api-0.1.8.dist-info/METADATA
tem_api-0.1.8.dist-info/WHEEL
tem_api-0.1.8.dist-info/top_level.txt
tem_api-0.1.8.dist-info/RECORD
