Metadata-Version: 2.1
Name: tem-api
Version: 0.1.8
Summary: Python API lib for TEM (https://tronenergy.market/) 
Home-page: https://github.com/8ByteCore8/tem-api
Author: Bohdan Kushnir
Author-email: 
License: MIT License
Project-URL: Source, https://github.com/8ByteCore8/tem-api
Keywords: tem,api,tron
Classifier: Development Status :: 3 - Alpha
Classifier: Intended Audience :: Developers
Classifier: License :: OSI Approved :: MIT License
Classifier: Programming Language :: Python :: 3.9
Classifier: Programming Language :: Python :: 3.10
Classifier: Programming Language :: Python :: 3.11
Classifier: Programming Language :: Python :: 3.12
Classifier: Programming Language :: Python :: 3.13
Requires-Python: >=3.6
License-File: LICENSE
Requires-Dist: aiohttp>=3.11.2
Requires-Dist: pydantic>=2.9.2
Provides-Extra: test
Requires-Dist: ruff==0.7.4; extra == "test"
